<?xml version="1.0" encoding="utf-8"?>
<photos>
	<photo>
		<filename>12 090_n.JPG</filename>
		<title>Diadema Piruleta</title>
		<description>
			Diadema de 1 cm con piruleta realizada en cinta de raso con pasamanería azul cielo
			<span class="highlight">Ref: V12/06/az</span>
			Diadema de 1 cm con piruleta realizada en cinta de raso con pasamanería rojo
			<span class="highlight">Ref: V12/06/rj</span>
			<p>* Diferentes combinaciones. Consultar colores.</p>
		</description>
	</photo>
	<photo>
		<filename>12 092_n.JPG</filename>
		<title>Capricho</title>
		<description>
			<p>Caprichosa Diadema de 2 cm realizada en cinta de raso y cinta de encaje en azul marino</p>
			<span class="highlight">Ref: V12/06/ma</span>
			<p></p><p>* Diferentes combinaciones. Consultar colores.</p>
		</description>
	</photo>
	<photo>
		<filename>2011 048.JPG</filename>
		<title>Diadema Rosas</title>
		<description><p>Diadema de lana  con dos pequeñas rosas</p>
			<span class="highlight">Ref: i11/01/ma y i11/01gr</span>
			<p></p><p>* Diferentes combinaciones. Consultar colores.</p>
		</description>
	</photo>
	<photo>
		<filename>2011 042.JPG</filename>
		<title>Diadema Lazo</title>
		<description><p>Diadema de lana con lazo en color morado.</p>
			<span class="highlight">Ref: i11/02/mo</span>
			<p></p><p>* Diferentes combinaciones. Consultar colores.</p>
		</description>
	</photo>
	<photo>
		<filename>2011 054.JPG</filename>
		<title>Diadema Lazo</title>
		<description><p>Diadema de Lana con lazo en marrón.</p>
			<span class="highlight">Ref: i11/02/mr</span>
			<p></p><p>* Diferentes combinaciones. Consultar colores.</p>
		</description>
	</photo>
	<photo>
		<filename>Martorela_3148.jpg</filename>
		<title>Diadema Martorela</title>
		<description><p>Diadema de 2cm, realizada con cita de raso morada.</p>
			<span class="highlight">Ref: v10/16/mo</span>
		</description>
	</photo>
	<photo>
		<filename>Martorela09202.jpg</filename>
		<title>Diadema Nido</title>
		<description><p>Diadema Nido en gris y rosa</p>
			<span class="highlight">Ref: v10/12/gr</span>
		</description>
	</photo>
	<photo>
		<filename>Martorela09207.jpg</filename>
		<title>Diadema Nido</title>
		<description><p>Diadema Nido en azul marino</p>
			<span class="highlight">Ref: v10/12/ma</span>
		</description>
	</photo>
	<photo>
		<filename>Martorela09210.jpg</filename>
		<title>Diadema Nido</title>
		<description><p>Diadema Nido en malva y morado</p>
			<span class="highlight">Ref: v10/12/ml</span>
		</description>
	</photo>
	<photo>
		<filename>Martorela09213.jpg</filename>
		<title>Diadema Nido</title>
		<description><p>Diadema Nido en granate y rosa</p>
			<span class="highlight">Ref: v10/12/gr</span>
		</description>
	</photo>	
	<photo>
		<filename>Martorela09221.jpg</filename>
		<title>Diadema Estrella</title>
		<description><p>Diadema Estrella en Terciopelo Granate con la estrella en gris perla, ideal para las ocasiones más especiales</p>
			<span class="highlight">Ref: v10/14/gg</span>
		</description>
	</photo>
	<photo>
		<filename>Martorela0901.jpg</filename>
		<title>Diadema Romántica</title>
		<description><p>Diadema Romántica con un bonito estampado y nido en rosa</p>
			<span class="highlight">Ref: v10/16/bg</span>
		</description>
	</photo>
	<photo>
		<filename>Martorela_3139.jpg</filename>
		<title>Lazo Ranita</title>
		<description><p>Ranita de 5cm con Lazo Clásico en Gris, Azul Cielo ó Rosa</p><span class="highlight">Ref: v10/18/gs</span><span class="highlight">Ref: v10/18/az</span><span class="highlight">Ref: v10/18/rs</span>
		</description>
	</photo>
	<photo>
		<filename>Martorela 2882.jpg</filename>
		<title>Lazo Pespunte</title>
		<description><p>Pasador con lazo pespunteado en raso verde, marrón ó azul marino, medidas 9cm</p><span class="highlight">Ref: v10/05/vr</span><span class="highlight">Ref: v10/05/mr</span><span class="highlight">Ref: v10/05/ma</span>
		</description>
	</photo>
	<photo>
		<filename>Martorela 539_.jpg</filename>
		<title>Lazo Pespunteado</title>
		<description><p>Pasador con lazo pespunteado de raso azul medidas 9cm</p><span class="highlight">Ref: v10/05/az</span><p>* Este pasador se puede hacer en otros colores, consultar disponibilidad</p></description>
	</photo>
	<photo>
		<filename>Martorela 545_.jpg</filename>
		<title>Romantico</title>
		<description><p>Pasador estampado medidas 5cm</p><span class="highlight">Ref: v10/05/bg</span></description>
	</photo>
	<photo>
		<filename>Martorela 009.jpg</filename>
		<title>Cerezas</title>
		<description><p>Pasador azul con cerzas medidas 5cm</p><span class="highlight">Ref: v10/04/az</span></description>
	</photo>
	<photo>
		<filename>Martorela 533_.jpg</filename>
		<title>Barquito</title>
		<description><p>Pasador de Chenille azul con cascabel medidas 6x4cm.</p>
			<span class="highlight">Ref: v10/01/az</span>
		</description>
	</photo>
	<photo>
		<filename>Martorela 034_.jpg</filename>
		<title>Barquito</title>
		<description><p>Pasador de Chenille rosa con cascabel medidas 6x4cm</p><span class="highlight">Ref: v10/01/rs</span></description>
	</photo>
	<photo>
		<filename>Martorela 532_.jpg</filename>
		<title>Barquito</title>
		<description><p>Pasador de Chenille verde con cascabel medidas 6x4cm</p><span class="highlight">Ref: v10/01/vr</span></description>
	</photo>
	<photo>
		<filename>Martorela 537_.jpg</filename>
		<title>Barquito</title>
		<description><p>Pasador de Chenille roja con cascabel medidas 6x4cm</p><span class="highlight">Ref: v10/01/rj</span></description>
	</photo>
	<photo>
		<filename>Martorela 535_.jpg</filename>
		<title>Barquito</title>
		<description><p>Pasador de Chenille marrón con cascabel medidas 6x4cm</p><span class="highlight">Ref: v10/01/mr</span></description>
	</photo>
</photos>
